cudamedfilt2d/__init__.py
cudamedfilt2d-1.0.dist-info/METADATA
cudamedfilt2d-1.0.dist-info/RECORD
cudamedfilt2d-1.0.dist-info/WHEEL
cudamedfilt2d-1.0.dist-info/top_level.txt
