Metadata-Version: 2.1
Name: cudamedfilt2d
Version: 1.0
Summary: A replacement for scipy.signal's medfilt2d() function using pycdua
Home-page: https://github.com/Jackmastr/cudamedfilt2d
Author: Jackson Sipple
Author-email: UNKNOWN
License: UNKNOWN
Platform: UNKNOWN
